ff_stats/__init__.py
ff_stats/fantasy_stats/__init__.py
ff_stats/fantasy_stats/fantasy_manager.py
ff_stats/fantasy_stats/settings.py
ff_stats/fantasy_stats/utils.py
ff_stats/fantasy_stats/info/__init__.py
ff_stats/fantasy_stats/info/espn_league_info.py
ff_stats/fantasy_stats/info/season_info.py
ff_stats/fantasy_stats/scrapes/__init__.py
ff_stats/fantasy_stats/scrapes/corrections.py
ff_stats/fantasy_stats/scrapes/scrape_functions.py
ff_stats/fantasy_stats/scrapes/source_references.py
ff_stats/fantasy_stats/scrapes/standardization_references.py
ff_stats-0.1.3.dist-info/LICENSE.txt
ff_stats-0.1.3.dist-info/METADATA
ff_stats-0.1.3.dist-info/WHEEL
ff_stats-0.1.3.dist-info/top_level.txt
ff_stats-0.1.3.dist-info/RECORD
