Metadata-Version: 2.1
Name: ff-stats
Version: 0.1.3
Summary: A package to pull fantasy football projections.
Home-page: UNKNOWN
Author: Patrick McCullough
License: UNKNOWN
Platform: UNKNOWN
Classifier: Programming Language :: Python :: 3
Classifier: License :: OSI Approved :: MIT License
Classifier: Operating System :: OS Independent
Requires-Python: >=3
Requires-Dist: pandas (>1.0.0)
Requires-Dist: requests (>=2.0.0)
